README.md
pyproject.toml
setup.cfg
setup.py
pyk4a/__init__.py
pyk4a/calibration.py
pyk4a/capture.py
pyk4a/config.py
pyk4a/errors.py
pyk4a/module.py
pyk4a/playback.py
pyk4a/py.typed
pyk4a/pyk4a.cpp
pyk4a/pyk4a.py
pyk4a/record.py
pyk4a/results.py
pyk4a/transformation.py
pyk4a/win32_utils.py
pyk4a.egg-info/PKG-INFO
pyk4a.egg-info/SOURCES.txt
pyk4a.egg-info/dependency_links.txt
pyk4a.egg-info/requires.txt
pyk4a.egg-info/top_level.txt