Metadata-Version: 2.1
Name: pyk4a
Version: 1.4.0
Summary: Python wrapper over Azure Kinect SDK
Home-page: https://github.com/etiennedub/pyk4a/
License: UNKNOWN
Platform: UNKNOWN
Classifier: Operating System :: OS Independent
Classifier: License :: OSI Approved :: MIT License
Classifier: Development Status :: 4 - Beta
Classifier: Topic :: Multimedia :: Video :: Capture
Classifier: Programming Language :: Python :: 3
Classifier: Programming Language :: C
